ringdown/__init__.py
ringdown/data.py
ringdown/fit.py
ringdown/indexing.py
ringdown/model.py
ringdown/qnms.py
ringdown/result.py
ringdown/target.py
ringdown/utils/__init__.py
ringdown/utils/imr.py
ringdown/utils/kde_contour.py
ringdown/utils/swsh.py
ringdown/utils/utils.py
ringdown/waveforms/__init__.py
ringdown/waveforms/coalescence.py
ringdown/waveforms/core.py
ringdown/waveforms/ringdown.py
ringdown-1.0.0.data/scripts/ringdown_fit
ringdown-1.0.0.data/scripts/ringdown_pipe
ringdown-1.0.0.dist-info/LICENSE
ringdown-1.0.0.dist-info/METADATA
ringdown-1.0.0.dist-info/WHEEL
ringdown-1.0.0.dist-info/top_level.txt
ringdown-1.0.0.dist-info/RECORD
