Metadata-Version: 2.1
Name: ringdown
Version: 1.0.0
Summary: Bayesian analysis of black hole ringdowns in gravitational-wave data.
Home-page: https://github.com/maxisi/ringdown
Author: Maximiliano Isi, Will M. Farr
Author-email: max.isi@ligo.org, will.farr@stonybrook.edu
License: MIT
Classifier: Development Status :: 3 - Alpha
Classifier: Intended Audience :: Science/Research
Classifier: License :: OSI Approved :: MIT License
Classifier: Operating System :: OS Independent
Classifier: Programming Language :: Python :: 3
Classifier: Topic :: Scientific/Engineering :: Astronomy
Requires-Python: >=3.10
License-File: LICENSE
Requires-Dist: numpy==1.26.4
Requires-Dist: lalsuite==7.23
Requires-Dist: h5py~=3.11
Requires-Dist: arviz~=0.19
Requires-Dist: pandas~=2.2
Requires-Dist: qnm==0.4.3
Requires-Dist: seaborn~=0.13
Requires-Dist: numpyro~=0.15
Requires-Dist: jax~=0.4
Requires-Dist: parse>=1.20
